<?xml version="1.0" encoding="utf-8"?>
<key id="d4afa8b0-032a-48a2-a56d-9245e8a9ba43" version="1">
  <creationDate>2025-01-24T12:11:06.29491Z</creationDate>
  <activationDate>2025-01-24T12:11:06.2841852Z</activationDate>
  <expirationDate>2025-04-24T12:11:06.2841852Z</expirationDate>
  <descriptor deserializerType="Microsoft.AspNetCore.DataProtection.AuthenticatedEncryption.ConfigurationModel.AuthenticatedEncryptorDescriptorDeserializer, Microsoft.AspNetCore.DataProtection, Version=6.0.0.0, Culture=neutral, PublicKeyToken=adb9793829ddae60">
    <descriptor>
      <encryption algorithm="AES_256_CBC" />
      <validation algorithm="HMACSHA256" />
      <masterKey p4:requiresEncryption="true" xmlns:p4="http://schemas.asp.net/2015/03/dataProtection">
        <!-- Warning: the key below is in an unencrypted form. -->
        <value>zLNNr0PcT/ET75MtgveiwA7PKNCxCc1OXqVk9QzgDa0NvDiMc/Np4W92IeGbR3F5Yi3dgEHuv64rvKv20iRLLg==</value>
      </masterKey>
    </descriptor>
  </descriptor>
</key>